hpl/__init__.py
hpl/ast.py
hpl/exceptions.py
hpl/grammar.py
hpl/logic.py
hpl/parser.py
hpl/visitor.py
hpl/grammars/files.lark
hpl/grammars/predicates.lark
hpl/grammars/properties.lark
hpl/grammars/tokens.lark
rigel_hpl-0.1.0.data/scripts/build_grammars
rigel_hpl-0.1.0.dist-info/LICENSE
rigel_hpl-0.1.0.dist-info/METADATA
rigel_hpl-0.1.0.dist-info/WHEEL
rigel_hpl-0.1.0.dist-info/top_level.txt
rigel_hpl-0.1.0.dist-info/RECORD
